LICENSE
MANIFEST.in
setup.py
src/django_project_templates/__init__.py
src/django_project_templates/pastertemplates.py
src/django_project_templates.egg-info/PKG-INFO
src/django_project_templates.egg-info/SOURCES.txt
src/django_project_templates.egg-info/dependency_links.txt
src/django_project_templates.egg-info/entry_points.txt
src/django_project_templates.egg-info/not-zip-safe
src/django_project_templates.egg-info/requires.txt
src/django_project_templates.egg-info/top_level.txt
src/django_project_templates/templates/.DS_Store
src/django_project_templates/templates/django_cruisecontrol_template/+project+.xml_tmpl
src/django_project_templates/templates/django_project/.DS_Store
src/django_project_templates/templates/django_project/build.xml_tmpl
src/django_project_templates/templates/django_project/fabfile.py_tmpl
src/django_project_templates/templates/django_project/requirements.txt
src/django_project_templates/templates/django_project/+project+/.DS_Store
src/django_project_templates/templates/django_project/+project+/__init__.py
src/django_project_templates/templates/django_project/+project+/__init__.pyc
src/django_project_templates/templates/django_project/+project+/apps/.DS_Store
src/django_project_templates/templates/django_project/+project+/apps/__init__.py
src/django_project_templates/templates/django_project/+project+/apps/__init__.pyc
src/django_project_templates/templates/django_project/+project+/assets/css/reset.css
src/django_project_templates/templates/django_project/+project+/configs/.DS_Store
src/django_project_templates/templates/django_project/+project+/configs/__init__.py
src/django_project_templates/templates/django_project/+project+/configs/__init__.pyc
src/django_project_templates/templates/django_project/+project+/configs/common/+project+_tmpl
src/django_project_templates/templates/django_project/+project+/configs/common/__init__.py
src/django_project_templates/templates/django_project/+project+/configs/common/__init__.pyc
src/django_project_templates/templates/django_project/+project+/configs/common/common.wsgi_tmpl
src/django_project_templates/templates/django_project/+project+/configs/common/local_settings.py
src/django_project_templates/templates/django_project/+project+/configs/common/manage.py
src/django_project_templates/templates/django_project/+project+/configs/common/settings.py_tmpl
