Metadata-Version: 1.0
Name: django-project-templates
Version: 0.11
Summary: Paster templates for creating Django projects
Home-page: http://github.com/garethr/django-project-templates/
Author: Gareth Rushgrove
Author-email: gareth@morethanseven.net
License: MIT
Keywords: django paster
Platform: UNKNOWN
Classifier: Intended Audience :: Developers
Classifier: License :: OSI Approved :: MIT License
Classifier: Operating System :: OS Independent
Classifier: Programming Language :: Python
